{"ast":[null,{"children":[2,3,12],"kind":"file","start":[0,0]},{"end":[7,0],"kind":"prelude","start":[7,0]},{"children":[4,6,8,10],"end":[8,0],"kind":"imports","start":[8,0]},{"children":[5],"end":[8,0],"kind":"import","start":[8,0]},{"end":[8,7],"kind":"module","start":[8,7],"value":["init","meta","widget","basic"]},{"children":[7],"end":[9,0],"kind":"import","start":[9,0]},{"end":[9,7],"kind":"module","start":[9,7],"value":["init","meta","lean","parser"]},{"children":[9],"end":[10,0],"kind":"import","start":[10,0]},{"end":[10,7],"kind":"module","start":[10,7],"value":["init","meta","interactive_base"]},{"children":[11],"end":[11,0],"kind":"import","start":[11,0]},{"end":[11,7],"kind":"module","start":[11,7],"value":["init","data","punit"]},{"children":[13,16,19,22,25,35,199],"end":[11,7],"kind":"commands","start":[11,7]},{"children":[14],"end":[12,9],"kind":"open","start":[12,0]},{"children":[15,0],"end":[12,5],"kind":"group","start":[12,5]},{"end":[12,5],"kind":"ident","start":[12,5],"value":"lean"},{"children":[17],"end":[13,16],"kind":"open","start":[13,0]},{"children":[18,0],"end":[13,5],"kind":"group","start":[13,5]},{"end":[13,5],"kind":"ident","start":[13,5],"value":["lean","parser"]},{"children":[20],"end":[14,16],"kind":"open","start":[14,0]},{"children":[21,0],"end":[14,5],"kind":"group","start":[14,5]},{"end":[14,5],"kind":"ident","start":[14,5],"value":"interactive"},{"children":[23],"end":[15,11],"kind":"open","start":[15,0]},{"children":[24,0],"end":[15,5],"kind":"group","start":[15,5]},{"end":[15,5],"kind":"ident","start":[15,5],"value":"tactic"},{"children":[26],"end":[16,11],"kind":"open","start":[16,0]},{"children":[27,0],"end":[16,5],"kind":"group","start":[16,5]},{"end":[16,5],"kind":"ident","start":[16,5],"value":"widget"},{"end":[18,0],"kind":"doc","start":[18,0],"value":" Accepts terms with the type `component tactic_state empty` or `html empty` and\nrenders them interactively. "},{"children":[28,30,34],"end":[20,0],"kind":"modifiers","start":[20,0]},{"children":[31],"end":[33,9],"kind":"@[","start":[20,0]},{"children":[33],"end":[20,2],"kind":"attrs","start":[20,2]},null,{"children":[0,0],"end":[20,14],"kind":"attr","start":[20,2],"value":"user_command"},{"end":[21,0],"kind":"meta","start":[21,0]},{"children":[29,0,0,36,37,52,198,0],"end":[33,9],"kind":"definition","start":[21,5]},{"end":[21,9],"kind":"ident","start":[21,9],"value":"show_widget_cmd"},{"children":[39],"end":[21,25],"kind":"binders","start":[21,25]},{"children":[40],"end":[21,26],"kind":"vars","start":[21,26]},{"children":[38,0,47],"end":[21,26],"kind":"binder_0","start":[21,26]},{"end":[21,26],"kind":"ident","start":[21,26],"value":"x"},{"end":[21,30],"kind":"ident","start":[21,30],"value":"parse"},{"children":[41,0],"end":[21,35],"kind":"const","pexpr":1,"start":[21,30]},{"end":[21,38],"kind":"ident","start":[21,38],"value":"tk"},{"children":[43,0],"end":[21,40],"kind":"const","pexpr":2,"start":[21,38]},{"end":[21,48],"kind":"string","pexpr":3,"start":[21,41],"value":"#html"},{"children":[44,45],"end":[21,48],"kind":"app","pexpr":4,"start":[21,38]},{"children":[42,46],"end":[21,48],"kind":"notation","pexpr":5,"start":[21,36],"value":"expr $ "},{"end":[21,52],"kind":"ident","start":[21,52],"value":"parser"},{"children":[48,0],"end":[21,58],"kind":"const","pexpr":6,"start":[21,52]},{"end":[21,59],"kind":"ident","start":[21,59],"value":"unit"},{"children":[50,0],"end":[21,63],"kind":"const","pexpr":7,"start":[21,59]},{"children":[49,51],"end":[21,63],"kind":"app","pexpr":8,"start":[21,52]},{"children":[60,66,159,177,189],"end":[33,9],"kind":"do","pexpr":148,"start":[21,67]},{"children":[55,56],"end":[22,7],"kind":"⟨","pexpr":153,"start":[22,2]},{"end":[22,9],"kind":"ident","pexpr":155,"start":[22,3],"value":"l"},{"end":[22,9],"kind":"ident","pexpr":157,"start":[22,5],"value":"c"},{"children":[54],"end":[22,7],"kind":"notation","pexpr":153,"start":[22,2],"value":"⟨"},{"end":[22,10],"kind":"ident","start":[22,10],"value":"cur_pos"},{"children":[58,0],"end":[22,17],"kind":"const","pexpr":11,"start":[22,10]},{"children":[57,0,59,0],"end":[22,17],"kind":"<-","start":[22,2]},{"end":[23,5],"kind":"ident","pexpr":159,"start":[23,2],"value":"y"},{"end":[23,6],"kind":"ident","start":[23,6],"value":["parser","pexpr"]},{"children":[62,0],"end":[23,18],"kind":"const","pexpr":27,"start":[23,6]},{"end":[23,20],"kind":"nat","pexpr":28,"start":[23,19],"value":"0"},{"children":[63,64],"end":[23,20],"kind":"app","pexpr":29,"start":[23,6]},{"children":[61,0,65,0],"end":[23,20],"kind":"<-","start":[23,2]},{"end":[24,8],"kind":"ident","pexpr":161,"start":[24,2],"value":"comp"},{"end":[24,9],"kind":"ident","start":[24,9],"value":["parser","of_tactic"]},{"children":[68,0],"end":[24,25],"kind":"const","pexpr":34,"start":[24,9]},{"children":[86],"end":[25,54],"kind":"do","pexpr":163,"start":[24,28]},{"end":[25,21],"kind":"ident","pexpr":165,"start":[25,4],"value":["tactic","eval_pexpr"]},{"end":[25,32],"kind":"ident","pexpr":167,"start":[25,23],"value":"component"},{"end":[25,45],"kind":"ident","pexpr":169,"start":[25,33],"value":"tactic_state"},{"children":[72,73],"end":[25,45],"kind":"app","pexpr":170,"start":[25,23]},{"end":[25,51],"kind":"ident","pexpr":172,"start":[25,46],"value":"empty"},{"children":[74,75],"end":[25,51],"kind":"app","pexpr":173,"start":[25,23]},{"children":[76],"end":[25,52],"kind":"(","pexpr":173,"start":[25,22]},{"children":[77],"end":[25,52],"kind":"notation","pexpr":173,"start":[25,22],"value":"("},{"children":[71,78],"end":[25,52],"kind":"app","pexpr":174,"start":[25,4]},{"end":[25,54],"kind":"ident","pexpr":162,"start":[25,53],"value":"y"},{"children":[79,80],"end":[25,54],"kind":"app","pexpr":177,"start":[25,4]},null,null,null,null,{"children":[81],"end":[26,2],"kind":"eval","start":[25,4]},{"children":[70],"end":[25,54],"kind":"notation","pexpr":163,"start":[24,28],"value":"do"},{"children":[87],"end":[26,3],"kind":"(","pexpr":163,"start":[24,27]},{"children":[88],"end":[26,3],"kind":"notation","pexpr":163,"start":[24,27],"value":"("},{"children":[109,136,147],"end":[29,63],"kind":"do","pexpr":181,"start":[26,9]},{"end":[27,7],"kind":"ident","pexpr":183,"start":[27,4],"value":"htm"},{"end":[27,10],"kind":"ident","start":[27,10],"value":"html"},{"children":[92,0],"end":[27,14],"kind":"const","pexpr":56,"start":[27,10]},{"end":[27,15],"kind":"ident","start":[27,15],"value":"empty"},{"children":[94,0],"end":[27,20],"kind":"const","pexpr":57,"start":[27,15]},{"children":[93,95],"end":[27,20],"kind":"app","pexpr":58,"start":[27,10]},{"end":[27,23],"kind":"ident","start":[27,23],"value":["tactic","eval_pexpr"]},{"children":[97,0],"end":[27,40],"kind":"const","pexpr":48,"start":[27,23]},{"end":[27,42],"kind":"ident","start":[27,42],"value":"html"},{"children":[99,0],"end":[27,46],"kind":"const","pexpr":49,"start":[27,42]},{"end":[27,47],"kind":"ident","start":[27,47],"value":"empty"},{"children":[101,0],"end":[27,52],"kind":"const","pexpr":50,"start":[27,47]},{"children":[100,102],"end":[27,52],"kind":"app","pexpr":51,"start":[27,42]},{"children":[103],"end":[27,53],"kind":"(","pexpr":51,"start":[27,41]},{"children":[104],"end":[27,53],"kind":"notation","pexpr":51,"start":[27,41],"value":"("},{"children":[98,105],"end":[27,53],"kind":"app","pexpr":52,"start":[27,23]},{"end":[27,55],"kind":"ident","pexpr":178,"start":[27,54],"value":"y"},{"children":[106,107],"end":[27,55],"kind":"app","pexpr":179,"start":[27,23]},{"children":[91,96,108,0],"end":[27,55],"kind":"<-","start":[27,4]},{"end":[28,5],"kind":"ident","pexpr":185,"start":[28,4],"value":"c"},{"end":[28,8],"kind":"ident","start":[28,8],"value":"component"},{"children":[111,0],"end":[28,17],"kind":"const","pexpr":73,"start":[28,8]},{"end":[28,18],"kind":"ident","start":[28,18],"value":"unit"},{"children":[113,0],"end":[28,22],"kind":"const","pexpr":74,"start":[28,18]},{"children":[112,114],"end":[28,22],"kind":"app","pexpr":75,"start":[28,8]},{"end":[28,23],"kind":"ident","start":[28,23],"value":"empty"},{"children":[116,0],"end":[28,28],"kind":"const","pexpr":76,"start":[28,23]},{"children":[115,117],"end":[28,28],"kind":"app","pexpr":77,"start":[28,8]},{"end":[28,31],"kind":"ident","start":[28,31],"value":"pure"},{"children":[119,0],"end":[28,35],"kind":"const","pexpr":61,"start":[28,31]},{"end":[28,38],"kind":"ident","start":[28,38],"value":["component","stateless"]},{"children":[121,0],"end":[28,57],"kind":"const","pexpr":62,"start":[28,38]},{"children":[126],"end":[28,61],"kind":"binders","start":[28,61]},{"children":[123,130],"end":[28,69],"kind":"fun","pexpr":189,"start":[28,59]},{"children":[127],"end":[28,61],"kind":"vars","start":[28,61]},{"children":[125,0,0],"end":[28,61],"kind":"binder_0","start":[28,61]},{"end":[28,61],"kind":"_","start":[28,61]},{"end":[28,68],"kind":"ident","pexpr":186,"start":[28,65],"value":"htm"},{"children":[128],"end":[28,69],"kind":"exprs","start":[28,69]},{"children":[129],"end":[28,69],"kind":"notation","pexpr":188,"start":[28,64],"value":"expr[ ,]"},{"children":[124],"end":[28,69],"kind":"notation","pexpr":189,"start":[28,59],"value":"fun"},{"children":[131],"end":[28,70],"kind":"(","pexpr":189,"start":[28,58]},{"children":[132],"end":[28,70],"kind":"notation","pexpr":189,"start":[28,58],"value":"("},{"children":[122,133],"end":[28,70],"kind":"app","pexpr":190,"start":[28,38]},{"children":[120,134],"end":[28,70],"kind":"notation","pexpr":191,"start":[28,36],"value":"expr $ "},{"children":[110,118,135,0],"end":[28,70],"kind":"<-","start":[28,4]},{"end":[29,8],"kind":"ident","pexpr":193,"start":[29,4],"value":"pure"},{"end":[29,33],"kind":"ident","pexpr":195,"start":[29,11],"value":["component","ignore_props"]},{"end":[29,59],"kind":"ident","pexpr":197,"start":[29,36],"value":["component","ignore_action"]},{"end":[29,63],"kind":"ident","pexpr":198,"start":[29,62],"value":"c"},{"children":[139,140],"end":[29,63],"kind":"notation","pexpr":201,"start":[29,60],"value":"expr $ "},{"children":[138,141],"end":[29,63],"kind":"notation","pexpr":202,"start":[29,34],"value":"expr $ "},{"children":[137,142],"end":[29,63],"kind":"notation","pexpr":203,"start":[29,9],"value":"expr $ "},null,null,null,{"children":[143],"end":[30,2],"kind":"eval","start":[29,4]},null,null,null,null,{"children":[90],"end":[29,63],"kind":"notation","pexpr":181,"start":[26,9],"value":"do"},{"children":[152],"end":[30,3],"kind":"(","pexpr":181,"start":[26,8]},{"children":[153],"end":[30,3],"kind":"notation","pexpr":181,"start":[26,8],"value":"("},{"children":[89,154],"end":[30,3],"kind":"notation","pexpr":205,"start":[26,4],"value":"expr <|> "},{"children":[155],"end":[30,4],"kind":"(","pexpr":205,"start":[24,26]},{"children":[156],"end":[30,4],"kind":"notation","pexpr":205,"start":[24,26],"value":"("},{"children":[69,157],"end":[30,4],"kind":"app","pexpr":206,"start":[24,9]},{"children":[67,0,158,0],"end":[30,4],"kind":"<-","start":[24,2]},{"end":[31,13],"kind":"ident","pexpr":208,"start":[31,2],"value":"save_widget"},{"children":[162,171],"end":[31,42],"kind":"⟨","pexpr":219,"start":[31,14]},{"end":[31,47],"kind":"ident","pexpr":220,"start":[31,15],"value":"l"},{"end":[31,47],"kind":"ident","pexpr":221,"start":[31,17],"value":"c"},{"end":[31,29],"kind":"string","pexpr":103,"start":[31,22],"value":"#html"},{"children":[164],"end":[31,30],"kind":"(","pexpr":103,"start":[31,21]},{"children":[165],"end":[31,30],"kind":"notation","pexpr":103,"start":[31,21],"value":"("},{"end":[31,30],"kind":"ident","start":[31,30],"value":"length"},{"children":[166,167],"end":[31,30],"kind":"field","pexpr":104,"start":[31,21]},{"children":[163,168],"end":[31,37],"kind":"notation","pexpr":215,"start":[31,19],"value":"expr - "},{"end":[31,41],"kind":"nat","pexpr":107,"start":[31,40],"value":"1"},{"children":[169,170],"end":[31,41],"kind":"notation","pexpr":217,"start":[31,38],"value":"expr - "},{"children":[161],"end":[31,42],"kind":"notation","pexpr":219,"start":[31,14],"value":"⟨"},{"children":[160,172],"end":[31,42],"kind":"app","pexpr":222,"start":[31,2]},{"end":[31,47],"kind":"ident","pexpr":223,"start":[31,43],"value":"comp"},{"children":[173,174],"end":[31,47],"kind":"app","pexpr":226,"start":[31,2]},null,{"children":[175],"end":[31,47],"kind":"eval","start":[31,2]},{"end":[32,7],"kind":"ident","pexpr":228,"start":[32,2],"value":"trace"},{"end":[32,38],"kind":"string","pexpr":119,"start":[32,8],"value":"successfully rendered widget"},{"children":[178,179],"end":[32,38],"kind":"app","pexpr":229,"start":[32,2]},{"end":[33,6],"kind":"ident","pexpr":231,"start":[33,2],"value":"pure"},{"children":[180,181],"end":[33,6],"kind":"app","pexpr":232,"start":[32,2]},{"end":[33,9],"kind":"()","pexpr":123,"start":[33,7]},{"children":[183],"end":[33,9],"kind":"notation","pexpr":123,"start":[33,7],"value":"()"},{"children":[182,184],"end":[33,9],"kind":"app","pexpr":233,"start":[32,2]},null,null,null,{"children":[185],"end":[35,0],"kind":"eval","start":[32,2]},null,null,null,null,null,null,null,null,{"children":[53],"end":[33,9],"kind":"notation","pexpr":148,"start":[21,67],"value":"do"},{"children":[201],"end":[35,12],"kind":"run_cmd","start":[35,0]},{"end":[35,8],"kind":"ident","start":[35,8],"value":"skip"},{"children":[200,0],"end":[35,12],"kind":"const","pexpr":234,"start":[35,8]}],"comments":[{"end":[6,0],"start":[1,2],"text":"\nCopyright (c) E.W.Ayers. All rights reserved.\nReleased under Apache 2.0 license as described in the file LICENSE.\n\nAuthor: E.W.Ayers\n"}],"expr":[null,{"const":[["interactive","parse"],[]]},{"const":[["lean","parser","tk"],[]]},{"string_macro":{"args":[],"value":"#html"}},{"app":[2,3]},{"app":[1,4]},{"const":[["lean","parser"],[]]},{"const":["unit",[]]},{"app":[6,7]},{"const":[["has_bind","bind"],[]]},{"annotation":{"args":[9],"name":"no_info"}},{"const":[["lean","parser","cur_pos"],[]]},{"app":[10,11]},{"const":[[4,"_",38],[]]},{"const":[[4,"_",36],[]]},{"const":[[4,"_",0],[]]},{"const":[[4,"_",1],[]]},{"var":2},{"const":[[4,"_",2],[]]},{"var":1},{"app":[18,19]},{"var":0},{"app":[20,21]},{"annotation":{"args":[22],"name":"anonymous_constructor"}},{"app":[17,23]},{"const":[["has_bind","bind"],[]]},{"annotation":{"args":[25],"name":"no_info"}},{"const":[["lean","parser","pexpr"],[]]},{"prenum":{"args":[],"value":"0"}},{"app":[27,28]},{"app":[26,29]},{"const":[[4,"_",6],[]]},{"const":[["has_bind","bind"],[]]},{"annotation":{"args":[32],"name":"no_info"}},{"const":[["lean","parser","of_tactic"],[]]},{"const":[["has_orelse","orelse"],[]]},{"const":[["tactic","eval_pexpr"],[]]},{"const":[["widget","component"],[]]},{"const":["tactic_state",[]]},{"app":[37,38]},{"const":["empty",[]]},{"app":[39,40]},{"app":[36,41]},{"var":0},{"app":[42,43]},{"app":[35,44]},{"const":[["has_bind","bind"],[]]},{"annotation":{"args":[46],"name":"no_info"}},{"const":[["tactic","eval_pexpr"],[]]},{"const":[["widget","html"],[]]},{"const":["empty",[]]},{"app":[49,50]},{"app":[48,51]},{"var":0},{"app":[52,53]},{"app":[47,54]},{"const":[["widget","html"],[]]},{"const":["empty",[]]},{"app":[56,57]},{"const":[["has_bind","bind"],[]]},{"annotation":{"args":[59],"name":"no_info"}},{"const":[["has_pure","pure"],[]]},{"const":[["widget","component","stateless"],[]]},{"const":[[4,"_",20],[]]},{"const":[["list","cons"],[]]},{"var":1},{"app":[64,65]},{"const":[["list","nil"],[]]},{"app":[66,67]},{"lam":{"bi":0,"body":68,"dom":63,"name":"_x"}},{"app":[62,69]},{"app":[61,70]},{"app":[60,71]},{"const":[["widget","component"],[]]},{"const":["unit",[]]},{"app":[73,74]},{"const":["empty",[]]},{"app":[75,76]},{"const":[["has_pure","pure"],[]]},{"const":[["widget","component","ignore_props"],[]]},{"const":[["widget","component","ignore_action"],[]]},{"var":0},{"app":[80,81]},{"app":[79,82]},{"app":[78,83]},{"lam":{"bi":0,"body":84,"dom":77,"name":"c"}},{"app":[72,85]},{"lam":{"bi":0,"body":86,"dom":58,"name":"htm"}},{"app":[55,87]},{"app":[45,88]},{"app":[34,89]},{"app":[33,90]},{"const":[[4,"_",9],[]]},{"const":[["has_bind","bind"],[]]},{"annotation":{"args":[93],"name":"no_info"}},{"const":[["tactic","save_widget"],[]]},{"const":[[4,"_",29],[]]},{"var":3},{"app":[96,97]},{"const":[["has_sub","sub"],[]]},{"const":[["has_sub","sub"],[]]},{"var":2},{"app":[100,101]},{"string_macro":{"args":[],"value":"#html"}},{"field_notation":{"args":[103],"field":"length","idx":0}},{"app":[102,104]},{"app":[99,105]},{"prenum":{"args":[],"value":"1"}},{"app":[106,107]},{"app":[98,108]},{"annotation":{"args":[109],"name":"anonymous_constructor"}},{"app":[95,110]},{"var":0},{"app":[111,112]},{"app":[94,113]},{"const":[[4,"_",35],[]]},{"const":["trace",[]]},{"const":[["tactic","trace"],[]]},{"choice":{"args":[116,117]}},{"string_macro":{"args":[],"value":"successfully rendered widget"}},{"app":[118,119]},{"const":[["has_pure","pure"],[]]},{"app":[120,121]},{"const":[["unit","star"],[]]},{"app":[122,123]},{"lam":{"bi":0,"body":124,"dom":115,"name":"_x"}},{"app":[114,125]},{"lam":{"bi":0,"body":126,"dom":92,"name":"comp"}},{"app":[91,127]},{"lam":{"bi":0,"body":128,"dom":31,"name":"y"}},{"app":[30,129]},{"equation":{"args":[24,130],"ignore_if_unused":false}},{"lam":{"bi":0,"body":131,"dom":16,"name":"c"}},{"lam":{"bi":0,"body":132,"dom":15,"name":"l"}},{"lam":{"bi":8,"body":133,"dom":14,"name":"_do_match"}},{"const":[[4,"_",37],[]]},{"var":1},{"var":0},{"app":[136,137]},{"const":["match_failed",[]]},{"annotation":{"args":[139],"name":"do_failure_eq"}},{"equation":{"args":[138,140],"ignore_if_unused":true}},{"lam":{"bi":0,"body":141,"dom":135,"name":"_x"}},{"lam":{"bi":8,"body":142,"dom":14,"name":"_do_match"}},{"equations":{"args":[134,143],"aux_lemmas":false,"fn_actual_names":[["show_widget_cmd","_match_1"]],"fn_names":[["show_widget_cmd","_match_1"]],"gen_code":false,"is_lemma":false,"is_meta":true,"is_noncomputable":false,"is_private":false,"num_fns":1,"prev_errors":false}},{"var":0},{"app":[144,145]},{"lam":{"bi":0,"body":146,"dom":13,"name":"_p"}},{"app":[12,147]},{"local":{"bi":0,"name":"l","pp":"l","type":15}},{"app":[18,149]},{"local":{"bi":0,"name":"c","pp":"c","type":16}},{"app":[150,151]},{"annotation":{"args":[152],"name":"anonymous_constructor"}},{"const":[[4,"_",4],[]]},{"local":{"bi":0,"name":"l","pp":"l","type":154}},{"const":[[4,"_",5],[]]},{"local":{"bi":0,"name":"c","pp":"c","type":156}},{"const":[[4,"_",8],[]]},{"local":{"bi":0,"name":"y","pp":"y","type":158}},{"const":[[4,"_",11],[]]},{"local":{"bi":0,"name":"comp","pp":"comp","type":160}},{"local":{"bi":0,"name":"y","pp":"y","type":31}},{"app":[42,162]},{"const":[[4,"_",12],[]]},{"local":{"bi":0,"name":["tactic","eval_pexpr"],"pp":["tactic","eval_pexpr"],"type":164}},{"const":[[4,"_",13],[]]},{"local":{"bi":0,"name":"component","pp":"component","type":166}},{"const":[[4,"_",14],[]]},{"local":{"bi":0,"name":"tactic_state","pp":"tactic_state","type":168}},{"app":[167,169]},{"const":[[4,"_",15],[]]},{"local":{"bi":0,"name":"empty","pp":"empty","type":171}},{"app":[170,172]},{"app":[165,173]},{"const":[[4,"_",16],[]]},{"local":{"bi":0,"name":"y","pp":"y","type":175}},{"app":[174,176]},{"local":{"bi":0,"name":"y","pp":"y","type":31}},{"app":[52,178]},{"app":[47,179]},{"app":[180,87]},{"const":[[4,"_",18],[]]},{"local":{"bi":0,"name":"htm","pp":"htm","type":182}},{"const":[[4,"_",19],[]]},{"local":{"bi":0,"name":"c","pp":"c","type":184}},{"local":{"bi":0,"name":"htm","pp":"htm","type":58}},{"app":[64,186]},{"app":[187,67]},{"lam":{"bi":0,"body":188,"dom":63,"name":"_x"}},{"app":[62,189]},{"app":[61,190]},{"const":[[4,"_",21],[]]},{"local":{"bi":0,"name":"pure","pp":"pure","type":192}},{"const":[[4,"_",22],[]]},{"local":{"bi":0,"name":["component","ignore_props"],"pp":["component","ignore_props"],"type":194}},{"const":[[4,"_",23],[]]},{"local":{"bi":0,"name":["component","ignore_action"],"pp":["component","ignore_action"],"type":196}},{"local":{"bi":0,"name":"c","pp":"c","type":77}},{"const":[[4,"_",24],[]]},{"local":{"bi":0,"name":"c","pp":"c","type":199}},{"app":[197,200]},{"app":[195,201]},{"app":[193,202]},{"app":[35,163]},{"app":[204,181]},{"app":[34,205]},{"const":[[4,"_",26],[]]},{"local":{"bi":0,"name":"save_widget","pp":"save_widget","type":207}},{"const":[[4,"_",27],[]]},{"local":{"bi":0,"name":"l","pp":"l","type":209}},{"app":[96,210]},{"const":[[4,"_",28],[]]},{"local":{"bi":0,"name":"c","pp":"c","type":212}},{"app":[100,213]},{"app":[214,104]},{"app":[99,215]},{"app":[216,107]},{"app":[211,217]},{"annotation":{"args":[218],"name":"anonymous_constructor"}},{"local":{"bi":0,"name":"l","pp":"l","type":15}},{"local":{"bi":0,"name":"c","pp":"c","type":16}},{"app":[208,219]},{"local":{"bi":0,"name":"comp","pp":"comp","type":92}},{"const":[[4,"_",30],[]]},{"local":{"bi":0,"name":"comp","pp":"comp","type":224}},{"app":[222,225]},{"const":[[4,"_",32],[]]},{"local":{"bi":0,"name":"trace","pp":"trace","type":227}},{"app":[228,119]},{"const":[[4,"_",33],[]]},{"local":{"bi":0,"name":"pure","pp":"pure","type":230}},{"app":[229,231]},{"app":[232,123]},{"const":[["tactic","skip"],[]]}],"file":1,"level":["0"]}