{"ast":[null,{"children":[2,3,6],"kind":"file","start":[0,0]},{"end":[6,0],"kind":"prelude","start":[6,0]},{"children":[4],"end":[7,0],"kind":"imports","start":[7,0]},{"children":[5],"end":[7,0],"kind":"import","start":[7,0]},{"end":[7,7],"kind":"module","start":[7,7],"value":["init","control","applicative"]},{"children":[7,10,13,55,66,114,119,124,205,238],"end":[7,7],"kind":"commands","start":[7,7]},{"children":[8,9],"end":[8,13],"kind":"universes","start":[8,0]},{"end":[8,10],"kind":"ident","start":[8,10],"value":"u"},{"end":[8,12],"kind":"ident","start":[8,12],"value":"v"},{"children":[11],"end":[10,13],"kind":"open","start":[10,0]},{"children":[12,0],"end":[10,5],"kind":"group","start":[10,5]},{"end":[10,5],"kind":"ident","start":[10,5],"value":"function"},{"children":[0,0,14,15,0,0,0,26],"end":[13,48],"kind":"class","start":[12,0]},{"end":[12,6],"kind":"ident","start":[12,6],"value":"has_bind"},{"children":[17],"end":[12,15],"kind":"binders","start":[12,15]},{"children":[18],"end":[12,16],"kind":"vars","start":[12,16]},{"children":[16,0,25],"end":[12,16],"kind":"binder_0","start":[12,16]},{"end":[12,16],"kind":"ident","start":[12,16],"value":"m"},{"children":[21],"end":[12,26],"kind":"Type","pexpr":1,"start":[12,20]},null,{"end":[12,25],"kind":"param","start":[12,25],"value":"u"},{"children":[24],"end":[12,35],"kind":"Type","pexpr":2,"start":[12,29]},null,{"end":[12,34],"kind":"param","start":[12,34],"value":"v"},{"children":[19,22],"end":[12,35],"kind":"notation","pexpr":3,"start":[12,27],"value":"->"},{"children":[28],"end":[13,0],"kind":"fields","start":[13,0]},{"children":[29],"end":[13,1],"kind":"vars","start":[13,1]},{"children":[27,0,0,54],"end":[13,1],"kind":"field_0","start":[13,1]},{"end":[13,1],"kind":"ident","start":[13,1],"value":"bind"},null,{"children":[33],"end":[13,10],"kind":"binders","start":[13,10]},{"children":[34,35],"end":[13,11],"kind":"vars","start":[13,11]},{"children":[32,0,36],"end":[13,11],"kind":"binder_4","start":[13,11]},{"end":[13,11],"kind":"ident","start":[13,11],"value":"α"},{"end":[13,13],"kind":"ident","start":[13,13],"value":"β"},{"children":[38],"end":[13,23],"kind":"Type","pexpr":4,"start":[13,17]},null,{"end":[13,22],"kind":"param","start":[13,22],"value":"u"},{"end":[13,27],"kind":"ident","pexpr":6,"start":[13,26],"value":"m"},{"end":[13,29],"kind":"ident","pexpr":7,"start":[13,28],"value":"α"},{"children":[39,40],"end":[13,29],"kind":"app","pexpr":8,"start":[13,26]},{"end":[13,34],"kind":"ident","pexpr":9,"start":[13,33],"value":"α"},{"end":[13,38],"kind":"ident","pexpr":10,"start":[13,37],"value":"m"},{"end":[13,40],"kind":"ident","pexpr":11,"start":[13,39],"value":"β"},{"children":[43,44],"end":[13,40],"kind":"app","pexpr":12,"start":[13,37]},{"children":[42,45],"end":[13,40],"kind":"notation","pexpr":13,"start":[13,35],"value":"->"},{"children":[46],"end":[13,41],"kind":"(","pexpr":13,"start":[13,32]},{"children":[47],"end":[13,41],"kind":"notation","pexpr":13,"start":[13,32],"value":"("},{"end":[13,45],"kind":"ident","pexpr":14,"start":[13,44],"value":"m"},{"end":[13,47],"kind":"ident","pexpr":15,"start":[13,46],"value":"β"},{"children":[49,50],"end":[13,47],"kind":"app","pexpr":16,"start":[13,44]},{"children":[48,51],"end":[13,47],"kind":"notation","pexpr":17,"start":[13,42],"value":"->"},{"children":[41,52],"end":[13,47],"kind":"notation","pexpr":18,"start":[13,30],"value":"->"},{"children":[31,53],"end":[13,47],"kind":"notation","pexpr":30,"start":[13,8],"value":"Pi"},{"children":[56],"end":[15,22],"kind":"export","start":[15,0]},{"children":[57,0,58],"end":[15,7],"kind":"group","start":[15,7]},{"end":[15,7],"kind":"ident","start":[15,7],"value":"has_bind"},{"children":[59],"end":[15,17],"kind":"explicit","start":[15,16]},{"end":[15,17],"kind":"ident","start":[15,17],"value":"bind"},{"children":[61],"end":[18,7],"kind":"@[","start":[17,0]},{"children":[63],"end":[17,2],"kind":"attrs","start":[17,2]},null,{"children":[0,0],"end":[17,8],"kind":"attr","start":[17,2],"value":"inline"},{"children":[60],"end":[17,10],"kind":"modifiers","start":[17,10]},null,{"children":[64,0,0,67,68,105,113,0],"end":[18,7],"kind":"definition","start":[17,10]},{"end":[17,14],"kind":"ident","start":[17,14],"value":["has_bind","and_then"]},{"children":[70,77,86,92,98],"end":[17,32],"kind":"binders","start":[17,32]},{"children":[71,72],"end":[17,33],"kind":"vars","start":[17,33]},{"children":[69,0,73],"end":[17,33],"kind":"binder_4","start":[17,33]},{"end":[17,33],"kind":"ident","start":[17,33],"value":"α"},{"end":[17,35],"kind":"ident","start":[17,35],"value":"β"},{"children":[75],"end":[17,45],"kind":"Type","pexpr":31,"start":[17,39]},null,{"end":[17,44],"kind":"param","start":[17,44],"value":"u"},{"children":[78],"end":[17,48],"kind":"vars","start":[17,48]},{"children":[76,0,85],"end":[17,48],"kind":"binder_4","start":[17,48]},{"end":[17,48],"kind":"ident","start":[17,48],"value":"m"},{"children":[81],"end":[17,58],"kind":"Type","pexpr":32,"start":[17,52]},null,{"end":[17,57],"kind":"param","start":[17,57],"value":"u"},{"children":[84],"end":[17,67],"kind":"Type","pexpr":33,"start":[17,61]},null,{"end":[17,66],"kind":"param","start":[17,66],"value":"v"},{"children":[79,82],"end":[17,67],"kind":"notation","pexpr":34,"start":[17,59],"value":"->"},{"children":[0,0,90],"end":[17,70],"kind":"binder_1","start":[17,70]},{"end":[17,79],"kind":"ident","start":[17,70],"value":"has_bind"},{"children":[87,0],"end":[17,78],"kind":"const","pexpr":35,"start":[17,70]},{"end":[17,80],"kind":"ident","pexpr":36,"start":[17,79],"value":"m"},{"children":[88,89],"end":[17,80],"kind":"app","pexpr":37,"start":[17,70]},{"children":[93],"end":[17,83],"kind":"vars","start":[17,83]},{"children":[91,0,96],"end":[17,83],"kind":"binder_0","start":[17,83]},{"end":[17,83],"kind":"ident","start":[17,83],"value":"x"},{"end":[17,88],"kind":"ident","pexpr":38,"start":[17,87],"value":"m"},{"end":[17,90],"kind":"ident","pexpr":39,"start":[17,89],"value":"α"},{"children":[94,95],"end":[17,90],"kind":"app","pexpr":40,"start":[17,87]},{"children":[99],"end":[17,93],"kind":"vars","start":[17,93]},{"children":[97,0,102],"end":[17,93],"kind":"binder_0","start":[17,93]},{"end":[17,93],"kind":"ident","start":[17,93],"value":"y"},{"end":[17,98],"kind":"ident","pexpr":41,"start":[17,97],"value":"m"},{"end":[17,100],"kind":"ident","pexpr":42,"start":[17,99],"value":"β"},{"children":[100,101],"end":[17,100],"kind":"app","pexpr":43,"start":[17,97]},{"end":[17,105],"kind":"ident","pexpr":44,"start":[17,104],"value":"m"},{"end":[17,107],"kind":"ident","pexpr":45,"start":[17,106],"value":"β"},{"children":[103,104],"end":[17,107],"kind":"app","pexpr":46,"start":[17,104]},{"children":[108,110],"end":[18,7],"kind":"do","pexpr":54,"start":[18,0]},{"end":[18,4],"kind":"ident","pexpr":49,"start":[18,3],"value":"x"},{"children":[107],"end":[18,4],"kind":"eval","start":[18,3]},{"end":[18,7],"kind":"ident","pexpr":52,"start":[18,6],"value":"y"},{"children":[109],"end":[20,0],"kind":"eval","start":[18,6]},null,null,{"children":[106],"end":[18,7],"kind":"notation","pexpr":54,"start":[18,0],"value":"do"},{"children":[0,0,0,115,116,118],"end":[20,25],"kind":"infixl","start":[20,0]},{"end":[20,7],"kind":"quoted","start":[20,7],"value":" >>= "},{"end":[20,15],"kind":"nat","start":[20,15],"value":"55"},{"end":[20,21],"kind":"ident","start":[20,21],"value":"bind"},{"children":[117,0],"end":[20,25],"kind":"const","pexpr":55,"start":[20,21]},{"children":[0,0,0,120,121,123],"end":[21,38],"kind":"infixl","start":[21,0]},{"end":[21,7],"kind":"quoted","start":[21,7],"value":" >> "},{"end":[21,14],"kind":"nat","start":[21,14],"value":"55"},{"end":[21,21],"kind":"ident","start":[21,21],"value":["has_bind","and_then"]},{"children":[122,0],"end":[21,38],"kind":"const","pexpr":56,"start":[21,21]},{"children":[0,0,125,126,137,148,0,157],"end":[25,33],"kind":"class","start":[23,0]},{"end":[23,6],"kind":"ident","start":[23,6],"value":"monad"},{"children":[128],"end":[23,12],"kind":"binders","start":[23,12]},{"children":[129],"end":[23,13],"kind":"vars","start":[23,13]},{"children":[127,0,136],"end":[23,13],"kind":"binder_0","start":[23,13]},{"end":[23,13],"kind":"ident","start":[23,13],"value":"m"},{"children":[132],"end":[23,23],"kind":"Type","pexpr":57,"start":[23,17]},null,{"end":[23,22],"kind":"param","start":[23,22],"value":"u"},{"children":[135],"end":[23,32],"kind":"Type","pexpr":58,"start":[23,26]},null,{"end":[23,31],"kind":"param","start":[23,31],"value":"v"},{"children":[130,133],"end":[23,32],"kind":"notation","pexpr":59,"start":[23,24],"value":"->"},{"children":[138,143],"end":[23,34],"kind":"extends","start":[23,34]},{"children":[0,0,142,0],"end":[23,42],"kind":"parent","start":[23,42]},{"end":[23,42],"kind":"ident","start":[23,42],"value":"applicative"},{"children":[139,0],"end":[23,53],"kind":"const","pexpr":60,"start":[23,42]},{"end":[23,55],"kind":"ident","pexpr":61,"start":[23,54],"value":"m"},{"children":[140,141],"end":[23,55],"kind":"app","pexpr":62,"start":[23,42]},{"children":[0,0,147,0],"end":[23,57],"kind":"parent","start":[23,57]},{"end":[23,57],"kind":"ident","start":[23,57],"value":"has_bind"},{"children":[144,0],"end":[23,65],"kind":"const","pexpr":63,"start":[23,57]},{"end":[23,67],"kind":"ident","pexpr":64,"start":[23,66],"value":"m"},{"children":[145,146],"end":[23,67],"kind":"app","pexpr":65,"start":[23,57]},{"children":[156],"end":[23,88],"kind":"Type","pexpr":66,"start":[23,70]},null,{"children":[154,155],"end":[23,76],"kind":"max","start":[23,76]},{"end":[23,81],"kind":"param","start":[23,81],"value":"u"},{"end":[23,83],"kind":"nat","start":[23,83],"value":"1"},{"children":[151,152],"end":[23,84],"kind":"+","start":[23,81]},{"children":[153],"end":[23,86],"kind":"(","start":[23,80]},{"end":[23,86],"kind":"param","start":[23,86],"value":"v"},{"children":[150],"end":[23,89],"kind":"(","start":[23,75]},{"children":[159,178],"end":[24,0],"kind":"fields","start":[24,0]},{"children":[160],"end":[24,1],"kind":"vars","start":[24,1]},{"children":[158,0,0,0,162],"end":[24,1],"kind":"field_0","start":[24,1]},{"end":[24,1],"kind":"ident","start":[24,1],"value":"map"},null,{"children":[176],"end":[24,5],"kind":":=","start":[24,5]},{"children":[166],"end":[24,10],"kind":"binders","start":[24,10]},{"children":[163,175],"end":[24,33],"kind":"fun","pexpr":112,"start":[24,8]},{"children":[167,168,169,170],"end":[24,10],"kind":"vars","start":[24,10]},{"children":[165,0,0],"end":[24,10],"kind":"binder_0","start":[24,10]},{"end":[24,10],"kind":"ident","start":[24,10],"value":"α"},{"end":[24,12],"kind":"ident","start":[24,12],"value":"β"},{"end":[24,14],"kind":"ident","start":[24,14],"value":"f"},{"end":[24,16],"kind":"ident","start":[24,16],"value":"x"},{"end":[24,20],"kind":"ident","pexpr":113,"start":[24,19],"value":"x"},{"end":[24,29],"kind":"ident","pexpr":104,"start":[24,25],"value":"pure"},{"end":[24,33],"kind":"ident","pexpr":114,"start":[24,32],"value":"f"},{"children":[172,173],"end":[24,33],"kind":"notation","pexpr":115,"start":[24,30],"value":"expr ∘ "},{"children":[171,174],"end":[24,33],"kind":"notation","pexpr":117,"start":[24,21],"value":"expr >>= "},{"children":[164],"end":[24,33],"kind":"notation","pexpr":112,"start":[24,8],"value":"fun"},{"children":[179],"end":[25,1],"kind":"vars","start":[25,1]},{"children":[177,0,0,0,181],"end":[25,1],"kind":"field_0","start":[25,1]},{"end":[25,1],"kind":"ident","start":[25,1],"value":"seq"},null,{"children":[196],"end":[25,5],"kind":":=","start":[25,5]},{"children":[185],"end":[25,10],"kind":"binders","start":[25,10]},{"children":[182,195],"end":[25,32],"kind":"fun","pexpr":137,"start":[25,8]},{"children":[186,187,188,189],"end":[25,10],"kind":"vars","start":[25,10]},{"children":[184,0,0],"end":[25,10],"kind":"binder_0","start":[25,10]},{"end":[25,10],"kind":"ident","start":[25,10],"value":"α"},{"end":[25,12],"kind":"ident","start":[25,12],"value":"β"},{"end":[25,14],"kind":"ident","start":[25,14],"value":"f"},{"end":[25,16],"kind":"ident","start":[25,16],"value":"x"},{"end":[25,20],"kind":"ident","pexpr":138,"start":[25,19],"value":"f"},{"children":[193,192],"end":[25,32],"kind":"infix_fn","pexpr":142,"start":[25,25]},{"end":[25,31],"kind":"ident","pexpr":139,"start":[25,30],"value":"x"},{"end":[25,32],"kind":"notation","start":[25,25],"value":"expr <$> "},{"children":[191],"end":[25,32],"kind":"notation","pexpr":142,"start":[25,25],"value":"("},{"children":[190,194],"end":[25,32],"kind":"notation","pexpr":144,"start":[25,21],"value":"expr >>= "},{"children":[183],"end":[25,32],"kind":"notation","pexpr":137,"start":[25,8],"value":"fun"},{"children":[198],"end":[28,4],"kind":"@[","start":[27,0]},{"children":[200,202],"end":[27,2],"kind":"attrs","start":[27,2]},null,{"children":[0,0],"end":[27,11],"kind":"attr","start":[27,2],"value":"reducible"},null,{"children":[0,0],"end":[27,19],"kind":"attr","start":[27,13],"value":"inline"},{"children":[197],"end":[27,21],"kind":"modifiers","start":[27,21]},null,{"children":[203,0,0,206,207,233,235,0],"end":[28,4],"kind":"definition","start":[27,21]},{"end":[27,25],"kind":"ident","start":[27,25],"value":"return"},{"children":[209,218,224],"end":[27,32],"kind":"binders","start":[27,32]},{"children":[210],"end":[27,33],"kind":"vars","start":[27,33]},{"children":[208,0,217],"end":[27,33],"kind":"binder_4","start":[27,33]},{"end":[27,33],"kind":"ident","start":[27,33],"value":"m"},{"children":[213],"end":[27,43],"kind":"Type","pexpr":145,"start":[27,37]},null,{"end":[27,42],"kind":"param","start":[27,42],"value":"u"},{"children":[216],"end":[27,52],"kind":"Type","pexpr":146,"start":[27,46]},null,{"end":[27,51],"kind":"param","start":[27,51],"value":"v"},{"children":[211,214],"end":[27,52],"kind":"notation","pexpr":147,"start":[27,44],"value":"->"},{"children":[0,0,222],"end":[27,55],"kind":"binder_1","start":[27,55]},{"end":[27,61],"kind":"ident","start":[27,55],"value":"monad"},{"children":[219,0],"end":[27,60],"kind":"const","pexpr":148,"start":[27,55]},{"end":[27,62],"kind":"ident","pexpr":149,"start":[27,61],"value":"m"},{"children":[220,221],"end":[27,62],"kind":"app","pexpr":150,"start":[27,55]},{"children":[225],"end":[27,65],"kind":"vars","start":[27,65]},{"children":[223,0,226],"end":[27,65],"kind":"binder_4","start":[27,65]},{"end":[27,65],"kind":"ident","start":[27,65],"value":"α"},{"children":[228],"end":[27,75],"kind":"Type","pexpr":151,"start":[27,69]},null,{"end":[27,74],"kind":"param","start":[27,74],"value":"u"},{"end":[27,80],"kind":"ident","pexpr":152,"start":[27,79],"value":"α"},{"end":[27,84],"kind":"ident","pexpr":153,"start":[27,83],"value":"m"},{"end":[27,86],"kind":"ident","pexpr":154,"start":[27,85],"value":"α"},{"children":[230,231],"end":[27,86],"kind":"app","pexpr":155,"start":[27,83]},{"children":[229,232],"end":[27,86],"kind":"notation","pexpr":156,"start":[27,81],"value":"->"},{"end":[28,0],"kind":"ident","start":[28,0],"value":"pure"},{"children":[234,0],"end":[28,4],"kind":"const","pexpr":157,"start":[28,0]},{"end":[30,0],"kind":"doc","start":[30,0],"value":" Identical to `has_bind.and_then`, but it is not inlined. "},{"children":[236],"end":[31,0],"kind":"modifiers","start":[31,0]},{"children":[237,0,0,239,240,277,285,0],"end":[32,7],"kind":"definition","start":[31,0]},{"end":[31,4],"kind":"ident","start":[31,4],"value":["has_bind","seq"]},{"children":[242,249,258,264,270],"end":[31,17],"kind":"binders","start":[31,17]},{"children":[243,244],"end":[31,18],"kind":"vars","start":[31,18]},{"children":[241,0,245],"end":[31,18],"kind":"binder_4","start":[31,18]},{"end":[31,18],"kind":"ident","start":[31,18],"value":"α"},{"end":[31,20],"kind":"ident","start":[31,20],"value":"β"},{"children":[247],"end":[31,30],"kind":"Type","pexpr":158,"start":[31,24]},null,{"end":[31,29],"kind":"param","start":[31,29],"value":"u"},{"children":[250],"end":[31,33],"kind":"vars","start":[31,33]},{"children":[248,0,257],"end":[31,33],"kind":"binder_4","start":[31,33]},{"end":[31,33],"kind":"ident","start":[31,33],"value":"m"},{"children":[253],"end":[31,43],"kind":"Type","pexpr":159,"start":[31,37]},null,{"end":[31,42],"kind":"param","start":[31,42],"value":"u"},{"children":[256],"end":[31,52],"kind":"Type","pexpr":160,"start":[31,46]},null,{"end":[31,51],"kind":"param","start":[31,51],"value":"v"},{"children":[251,254],"end":[31,52],"kind":"notation","pexpr":161,"start":[31,44],"value":"->"},{"children":[0,0,262],"end":[31,55],"kind":"binder_1","start":[31,55]},{"end":[31,64],"kind":"ident","start":[31,55],"value":"has_bind"},{"children":[259,0],"end":[31,63],"kind":"const","pexpr":162,"start":[31,55]},{"end":[31,65],"kind":"ident","pexpr":163,"start":[31,64],"value":"m"},{"children":[260,261],"end":[31,65],"kind":"app","pexpr":164,"start":[31,55]},{"children":[265],"end":[31,68],"kind":"vars","start":[31,68]},{"children":[263,0,268],"end":[31,68],"kind":"binder_0","start":[31,68]},{"end":[31,68],"kind":"ident","start":[31,68],"value":"x"},{"end":[31,73],"kind":"ident","pexpr":165,"start":[31,72],"value":"m"},{"end":[31,75],"kind":"ident","pexpr":166,"start":[31,74],"value":"α"},{"children":[266,267],"end":[31,75],"kind":"app","pexpr":167,"start":[31,72]},{"children":[271],"end":[31,78],"kind":"vars","start":[31,78]},{"children":[269,0,274],"end":[31,78],"kind":"binder_0","start":[31,78]},{"end":[31,78],"kind":"ident","start":[31,78],"value":"y"},{"end":[31,83],"kind":"ident","pexpr":168,"start":[31,82],"value":"m"},{"end":[31,85],"kind":"ident","pexpr":169,"start":[31,84],"value":"β"},{"children":[272,273],"end":[31,85],"kind":"app","pexpr":170,"start":[31,82]},{"end":[31,90],"kind":"ident","pexpr":171,"start":[31,89],"value":"m"},{"end":[31,92],"kind":"ident","pexpr":172,"start":[31,91],"value":"β"},{"children":[275,276],"end":[31,92],"kind":"app","pexpr":173,"start":[31,89]},{"children":[280,282],"end":[32,7],"kind":"do","pexpr":181,"start":[32,0]},{"end":[32,4],"kind":"ident","pexpr":176,"start":[32,3],"value":"x"},{"children":[279],"end":[32,4],"kind":"eval","start":[32,3]},{"end":[32,7],"kind":"ident","pexpr":179,"start":[32,6],"value":"y"},{"children":[281],"end":[32,7],"kind":"eval","start":[32,6]},null,null,{"children":[278],"end":[32,7],"kind":"notation","pexpr":181,"start":[32,0],"value":"do"}],"comments":[{"end":[5,0],"start":[1,2],"text":"\nCopyright (c) Luke Nelson and Jared Roesch. All rights reserved.\nReleased under Apache 2.0 license as described in the file LICENSE.\nAuthors: Leonardo de Moura, Luke Nelson, Jared Roesch, Sebastian Ullrich\n"}],"expr":[null,{"sort":2},{"sort":4},{"Pi":{"bi":0,"body":2,"dom":1,"name":"ᾰ"}},{"sort":2},{"Pi":{"bi":0,"body":2,"dom":1,"name":"ᾰ"}},{"local":{"bi":0,"name":"m","pp":"m","type":5}},{"local":{"bi":4,"name":"α","pp":"α","type":4}},{"app":[6,7]},{"local":{"bi":4,"name":"α","pp":"α","type":4}},{"local":{"bi":0,"name":"m","pp":"m","type":5}},{"local":{"bi":4,"name":"β","pp":"β","type":4}},{"app":[10,11]},{"Pi":{"bi":0,"body":12,"dom":9,"name":"ᾰ"}},{"local":{"bi":0,"name":"m","pp":"m","type":5}},{"local":{"bi":4,"name":"β","pp":"β","type":4}},{"app":[14,15]},{"Pi":{"bi":0,"body":16,"dom":13,"name":"ᾰ"}},{"Pi":{"bi":0,"body":17,"dom":8,"name":"ᾰ"}},{"var":1},{"app":[6,19]},{"var":2},{"var":2},{"app":[10,22]},{"Pi":{"bi":0,"body":23,"dom":21,"name":"ᾰ"}},{"var":2},{"app":[14,25]},{"Pi":{"bi":0,"body":26,"dom":24,"name":"ᾰ"}},{"Pi":{"bi":0,"body":27,"dom":20,"name":"ᾰ"}},{"Pi":{"bi":4,"body":28,"dom":4,"name":"β"}},{"Pi":{"bi":4,"body":29,"dom":4,"name":"α"}},{"sort":2},{"sort":2},{"sort":4},{"Pi":{"bi":0,"body":33,"dom":32,"name":"ᾰ"}},{"const":["has_bind",[]]},{"local":{"bi":4,"name":"m","pp":"m","type":34}},{"app":[35,36]},{"local":{"bi":4,"name":"m","pp":"m","type":34}},{"local":{"bi":4,"name":"α","pp":"α","type":31}},{"app":[38,39]},{"local":{"bi":4,"name":"m","pp":"m","type":34}},{"local":{"bi":4,"name":"β","pp":"β","type":31}},{"app":[41,42]},{"local":{"bi":4,"name":"m","pp":"m","type":34}},{"local":{"bi":4,"name":"β","pp":"β","type":31}},{"app":[44,45]},{"const":[["has_bind","bind"],[]]},{"annotation":{"args":[47],"name":"no_info"}},{"local":{"bi":0,"name":"x","pp":"x","type":40}},{"app":[48,49]},{"const":[[4,"_",7],[]]},{"local":{"bi":0,"name":"y","pp":"y","type":43}},{"lam":{"bi":0,"body":52,"dom":51,"name":"_x"}},{"app":[50,53]},{"const":[["has_bind","bind"],[]]},{"const":[["has_bind","and_then"],[]]},{"sort":2},{"sort":4},{"Pi":{"bi":0,"body":58,"dom":57,"name":"ᾰ"}},{"const":["applicative",[]]},{"local":{"bi":0,"name":"m","pp":"m","type":59}},{"app":[60,61]},{"const":["has_bind",[]]},{"local":{"bi":0,"name":"m","pp":"m","type":59}},{"app":[63,64]},{"sort":6},{"const":[[4,"_",39],[]]},{"const":[[4,"_",40],[]]},{"const":[[4,"_",41],[]]},{"const":[[4,"_",42],[]]},{"const":[["has_bind","bind"],[]]},{"var":0},{"app":[71,72]},{"const":[["function","comp"],[]]},{"sort":8},{"sort":10},{"Pi":{"bi":0,"body":76,"dom":75,"name":"ᾰ"}},{"annotation":{"args":[77],"name":"as_is"}},{"const":["has_pure",[7,9]]},{"var":0},{"app":[79,80]},{"annotation":{"args":[81],"name":"as_is"}},{"sort":8},{"var":3},{"var":1},{"app":[84,85]},{"Pi":{"bi":0,"body":86,"dom":80,"name":"ᾰ"}},{"Pi":{"bi":4,"body":87,"dom":83,"name":"α"}},{"annotation":{"args":[88],"name":"as_is"}},{"lam":{"bi":0,"body":89,"dom":82,"name":"self"}},{"lam":{"bi":4,"body":90,"dom":78,"name":"f"}},{"const":[["applicative","to_has_pure"],[]]},{"annotation":{"args":[92],"name":"@"}},{"const":[[4,"_",17],[]]},{"app":[93,94]},{"const":["applicative",[1,3]]},{"Pi":{"bi":0,"body":58,"dom":57,"name":"ᾰ"}},{"local":{"bi":0,"name":"m","pp":"m","type":97}},{"app":[96,98]},{"annotation":{"args":[99],"name":"as_is"}},{"local":{"bi":1,"name":"to_applicative","pp":"to_applicative","type":100}},{"app":[95,101]},{"app":[91,102]},{"local":{"bi":0,"name":"pure","pp":"pure","type":103}},{"app":[74,104]},{"var":1},{"app":[105,106]},{"app":[73,107]},{"lam":{"bi":0,"body":108,"dom":70,"name":"x"}},{"lam":{"bi":0,"body":109,"dom":69,"name":"f"}},{"lam":{"bi":0,"body":110,"dom":68,"name":"β"}},{"lam":{"bi":0,"body":111,"dom":67,"name":"α"}},{"local":{"bi":0,"name":"x","pp":"x","type":70}},{"local":{"bi":0,"name":"f","pp":"f","type":69}},{"app":[105,114]},{"app":[71,113]},{"app":[116,115]},{"const":[[4,"_",44],[]]},{"const":[[4,"_",45],[]]},{"const":[[4,"_",46],[]]},{"const":[[4,"_",47],[]]},{"const":[["has_bind","bind"],[]]},{"var":1},{"app":[122,123]},{"const":[[4,"_",48],[]]},{"const":[["functor","map"],[]]},{"var":0},{"app":[126,127]},{"var":1},{"app":[128,129]},{"lam":{"bi":0,"body":130,"dom":125,"name":"_x"}},{"annotation":{"args":[131],"name":"infix_fn"}},{"app":[124,132]},{"lam":{"bi":0,"body":133,"dom":121,"name":"x"}},{"lam":{"bi":0,"body":134,"dom":120,"name":"f"}},{"lam":{"bi":0,"body":135,"dom":119,"name":"β"}},{"lam":{"bi":0,"body":136,"dom":118,"name":"α"}},{"local":{"bi":0,"name":"f","pp":"f","type":120}},{"local":{"bi":0,"name":"x","pp":"x","type":121}},{"app":[128,139]},{"lam":{"bi":0,"body":140,"dom":125,"name":"_x"}},{"annotation":{"args":[141],"name":"infix_fn"}},{"app":[122,138]},{"app":[143,142]},{"sort":2},{"sort":4},{"Pi":{"bi":0,"body":146,"dom":145,"name":"ᾰ"}},{"const":["monad",[]]},{"local":{"bi":4,"name":"m","pp":"m","type":147}},{"app":[148,149]},{"sort":2},{"local":{"bi":4,"name":"α","pp":"α","type":151}},{"local":{"bi":4,"name":"m","pp":"m","type":147}},{"local":{"bi":4,"name":"α","pp":"α","type":151}},{"app":[153,154]},{"Pi":{"bi":0,"body":155,"dom":152,"name":"ᾰ"}},{"const":[["has_pure","pure"],[]]},{"sort":2},{"sort":2},{"sort":4},{"Pi":{"bi":0,"body":160,"dom":159,"name":"ᾰ"}},{"const":["has_bind",[]]},{"local":{"bi":4,"name":"m","pp":"m","type":161}},{"app":[162,163]},{"local":{"bi":4,"name":"m","pp":"m","type":161}},{"local":{"bi":4,"name":"α","pp":"α","type":158}},{"app":[165,166]},{"local":{"bi":4,"name":"m","pp":"m","type":161}},{"local":{"bi":4,"name":"β","pp":"β","type":158}},{"app":[168,169]},{"local":{"bi":4,"name":"m","pp":"m","type":161}},{"local":{"bi":4,"name":"β","pp":"β","type":158}},{"app":[171,172]},{"const":[["has_bind","bind"],[]]},{"annotation":{"args":[174],"name":"no_info"}},{"local":{"bi":0,"name":"x","pp":"x","type":167}},{"app":[175,176]},{"const":[[4,"_",55],[]]},{"local":{"bi":0,"name":"y","pp":"y","type":170}},{"lam":{"bi":0,"body":179,"dom":178,"name":"_x"}},{"app":[177,180]}],"file":1,"level":["0",{"param":"u"},{"suc":1},{"param":"v"},{"suc":3},{"max":[2,3]},{"suc":5},{"mvar":["_mlocal","_fresh",10,1230]},{"suc":7},{"mvar":["_mlocal","_fresh",10,1231]},{"suc":9}]}